{
  "$schema": "https://static.modelcontextprotocol.io/schemas/2025-12-11/server.schema.json",
  "name": "io.github.Br0ski777/weather-api",
  "title": "Weather API",
  "description": "Current weather and 7-day forecast for any location. OpenMeteo-powered. x402 micropayment.",
  "version": "1.0.1",
  "websiteUrl": "https://github.com/Br0ski777/weather-api-x402",
  "repository": {
    "url": "https://github.com/Br0ski777/weather-api-x402",
    "source": "github"
  },
  "remotes": [
    {
      "type": "sse",
      "url": "https://weather-api-x402-production.up.railway.app/mcp"
    }
  ]
}